Workbook

Sheet 📊 Dashboard
B2: FINANCIAL PERFORMANCE DASHBOARD
B3: Professional Business Financial Toolkit | FY 2025
B7: Total Revenue ($) | C7: Net Profit ($) | E7: Operating Margin | F7: Cash Balance ($)
B8: ='💰 Income Statement'!C27 -> 55500 | C8: ='💰 Income Statement'!C38 -> 185381.06 | E8: ='💰 Income Statement'!C40 -> 0.5205813 | F8: ='💵 Cash Flow'!C28 -> 41695
B9: ▲ vs Prior Year | C9: ▲ vs Prior Year | E9: ▲ vs Prior Year | F9: ▲ vs Prior Year
B13: ▸ NAVIGATE TO MODULE
B14: 💰 Income Statement | C14: 📋 Revenue, expenses & net profit
B15: 🏦 Balance Sheet | C15: 📋 Assets, liabilities & equity
B16: 💵 Cash Flow | C16: 📋 Operating, investing & financing
B17: 📈 Budget vs Actual | C17: 📋 Variance analysis by category
B18: ⚙️ Assumptions | C18: 📋 Central inputs & drivers
B21: CONFIDENTIAL | For internal use only | © 2025 RemedyData

Sheet ⚙️ Assumptions
B2: ⚙️ ASSUMPTIONS & KEY DRIVERS
B3: All highlighted cells (blue) are input fields.
B5: REVENUE ASSUMPTIONS
B6: Assumption | C6: Value | D6: Notes
B7: Base Revenue ($) | C7: 200000 | D7: Perfect
B8: YoY Revenue Growth Rate | C8: 0.12 | D8: Perfect
B9: Product Revenue Mix (%) | C9: 0.65 | D9: Perfect
B10: Services Revenue Mix (%) | C10: 0.35 | D10: Perfect
B12: COST ASSUMPTIONS
B13: Assumption | C13: Value | D13: Notes
B14: Cost of Goods Sold Margin | C14: 0.42 | D14: Perfect
B15: Operating Expense Growth | C15: 0.08 | D15: Perfect
B16: Salaries & Wages Ratio | C16: 0.25 | D16: Perfect
B17: Marketing Spend Ratio | C17: 0.07 | D17: Perfect
B18: Admin & Overhead Ratio | C18: 0.05 | D18: Perfect
B20: FINANCIAL ASSUMPTIONS
B21: Assumption | C21: Value | D21: Notes
B22: Tax Rate | C22: 0.25 | D22: Perfect
B23: Depreciation Rate | C23: 0.1 | D23: Perfect
B24: Interest Rate on Debt | C24: 0.055 | D24: Perfect
B25: Dividend Payout Ratio | C25: 0.3 | D25: Perfect
B27: BALANCE SHEET ASSUMPTIONS
B28: Assumption | C28: Value | D28: Notes
B29: Opening Cash Balance ($) | C29: 50000 | D29: Perfect
B30: Accounts Receivable Days | C30: 45 | D30: Perfect
B31: Accounts Payable Days | C31: 30 | D31: Perfect
B32: Inventory Days | C32: 60 | D32: Perfect
B33: Long-term Debt ($) | C33: 150000 | D33: Perfect

Sheet 💰 Income Statement
B2: 💰 INCOME STATEMENT - FY 2025
B3: Profit & Loss | January - December 2025
B5: Description | C5: Q1 ($) | D5: Q2 ($) | E5: Q3 ($) | F5: Q4 ($) | G5: FY Total ($)
B6: REVENUE
B7: Product Revenue | C7: ='⚙️ Assumptions'!C7*'⚙️ Assumptions'!C10 -> 70000 | D7: ='⚙️ Assumptions'!C7*'⚙️ Assumptions'!C10*(1+'⚙️ Assumptions'!C8) -> 78400 | E7: ='⚙️ Assumptions'!C7*'⚙️ Assumptions'!C10*(1+'⚙️ Assumptions'!C8)^2 -> 87808 | F7: ='⚙️ Assumptions'!C7*'⚙️ Assumptions'!C10*(1+'⚙️ Assumptions'!C8)^3 -> 98344.96 | G7: =SUM(C7:F7) -> 334552.96
B8: Services Revenue | C8: ='⚙️ Assumptions'!C7*'⚙️ Assumptions'!C11 -> 0 | D8: ='⚙️ Assumptions'!C7*'⚙️ Assumptions'!C11*(1+'⚙️ Assumptions'!C8) -> 0 | E8: ='⚙️ Assumptions'!C7*'⚙️ Assumptions'!C11*(1+'⚙️ Assumptions'!C8)^2 -> 0 | F8: ='⚙️ Assumptions'!C7*'⚙️ Assumptions'!C11*(1+'⚙️ Assumptions'!C8)^3 -> 0 | G8: =SUM(C8:F8) -> 0
B9: Other Revenue | C9: 5000 | D9: 5250 | E9: 5513 | F9: 5788 | G9: =SUM(C9:F9) -> 21551
B10: TOTAL REVENUE | C10: =SUM(C7:C9) -> 75000 | D10: =SUM(D7:D9) -> 83650 | E10: =SUM(E7:E9) -> 93321 | F10: =SUM(F7:F9) -> 104132.96 | G10: =SUM(C10:F10) -> 356103.96
B11: COST OF GOODS SOLD
B12: Direct Materials | C12: =C10*'⚙️ Assumptions'!C12*0.6 -> 0 | D12: =D10*'⚙️ Assumptions'!C12*0.6 -> 0 | E12: =E10*'⚙️ Assumptions'!C12*0.6 -> 0 | F12: =F10*'⚙️ Assumptions'!C12*0.6 -> 0 | G12: =SUM(C12:F12) -> 0
B13: Direct Labour | C13: =C10*'⚙️ Assumptions'!C12*0.3 -> 0 | D13: =D10*'⚙️ Assumptions'!C12*0.3 -> 0 | E13: =E10*'⚙️ Assumptions'!C12*0.3 -> 0 | F13: =F10*'⚙️ Assumptions'!C12*0.3 -> 0 | G13: =SUM(C13:F13) -> 0
B14: Manufacturing Overhead | C14: =C10*'⚙️ Assumptions'!C12*0.1 -> 0 | D14: =D10*'⚙️ Assumptions'!C12*0.1 -> 0 | E14: =E10*'⚙️ Assumptions'!C12*0.1 -> 0 | F14: =F10*'⚙️ Assumptions'!C12*0.1 -> 0 | G14: =SUM(C14:F14) -> 0
B15: TOTAL COGS | C15: =SUM(C12:C14) -> 0 | D15: =SUM(D12:D14) -> 0 | E15: =SUM(E12:E14) -> 0 | F15: =SUM(F12:F14) -> 0 | G15: =SUM(C15:F15) -> 0
B16: GROSS PROFIT | C16: =C10-C15 -> 75000 | D16: =D10-D15 -> 83650 | E16: =E10-E15 -> 93321 | F16: =F10-F15 -> 104132.96 | G16: =SUM(C16:F16) -> 356103.96
B17: OPERATING EXPENSES
B18: Salaries & Wages | C18: =C10*'⚙️ Assumptions'!C20 -> 0 | D18: =D10*'⚙️ Assumptions'!C20 -> 0 | E18: =E10*'⚙️ Assumptions'!C20 -> 0 | F18: =F10*'⚙️ Assumptions'!C20 -> 0 | G18: =SUM(C18:F18) -> 0
B19: Marketing & Advertising | C19: =C10*'⚙️ Assumptions'!C17 -> 5250 | D19: =D10*'⚙️ Assumptions'!C17 -> 5855.5 | E19: =E10*'⚙️ Assumptions'!C17 -> 6532.47 | F19: =F10*'⚙️ Assumptions'!C17 -> 7289.3072 | G19: =SUM(C19:F19) -> 24927.277
B20: Admin & Overhead | C20: =C10*'⚙️ Assumptions'!C18 -> 3750 | D20: =D10*'⚙️ Assumptions'!C18 -> 4182.5 | E20: =E10*'⚙️ Assumptions'!C18 -> 4666.05 | F20: =F10*'⚙️ Assumptions'!C18 -> 5206.648 | G20: =SUM(C20:F20) -> 17805.198
B21: Depreciation | C21: =C10*'⚙️ Assumptions'!C23 -> 7500 | D21: =D10*'⚙️ Assumptions'!C23 -> 8365 | E21: =E10*'⚙️ Assumptions'!C23 -> 9332.1 | F21: =F10*'⚙️ Assumptions'!C23 -> 10413.296 | G21: =SUM(C21:F21) -> 35610.396
B22: Other Operating Expenses | C22: 3000 | D22: 3150 | E22: 3308 | F22: 3473 | G22: =SUM(C22:F22) -> 12931
B23: TOTAL OPEX | C23: =SUM(C18:C22) -> 19500 | D23: =SUM(D18:D22) -> 21553 | E23: =SUM(E18:E22) -> 23838.62 | F23: =SUM(F18:F22) -> 26382.251 | G23: =SUM(C23:F23) -> 91273.871
B24: EBIT (Operating Profit) | C24: =C16-C23 -> 55500 | D24: =D16-D23 -> 62097 | E24: =E16-E23 -> 69482.38 | F24: =F16-F23 -> 77750.709 | G24: =SUM(C24:F24) -> 264830.09
B25: BELOW THE LINE
B26: Interest Expense | C26: ='⚙️ Assumptions'!C30*'⚙️ Assumptions'!C27/4 -> 0 | D26: ='⚙️ Assumptions'!C30*'⚙️ Assumptions'!C27/4 -> 0 | E26: ='⚙️ Assumptions'!C30*'⚙️ Assumptions'!C27/4 -> 0 | F26: ='⚙️ Assumptions'!C30*'⚙️ Assumptions'!C27/4 -> 0 | G26: =SUM(C26:F26) -> 0
B27: PROFIT BEFORE TAX | C27: =C24-C26 -> 55500 | D27: =D24-D26 -> 62097 | E27: =E24-E26 -> 69482.38 | F27: =F24-F26 -> 77750.709 | G27: =SUM(C27:F27) -> 264830.09
B28: Income Tax | C28: =IF(C27>0,C27*'⚙️ Assumptions'!C25,0) -> 16650 | D28: =IF(D27>0,D27*'⚙️ Assumptions'!C25,0) -> 18629.1 | E28: =IF(E27>0,E27*'⚙️ Assumptions'!C25,0) -> 20844.714 | F28: =IF(F27>0,F27*'⚙️ Assumptions'!C25,0) -> 23325.213 | G28: =SUM(C28:F28) -> 79449.027
B29: ★ NET PROFIT AFTER TAX | C29: =C27-C28 -> 38850 | D29: =D27-D28 -> 43467.9 | E29: =E27-E28 -> 48637.666 | F29: =F27-F28 -> 54425.496 | G29: =SUM(C29:F29) -> 185381.06
B31: KEY RATIOS
B32: Gross Profit Margin | C32: =C16/C10 -> 1 | D32: =D16/D10 -> 1 | E32: =E16/E10 -> 1 | F32: =F16/F10 -> 1 | G32: =AVERAGE(C32:F32) -> 1
B33: EBIT Margin | C33: =C24/C10 -> 0.74 | D33: =D24/D10 -> 0.7423431 | E33: =E24/E10 -> 0.74455246 | F33: =F24/F10 -> 0.74664841 | G33: =AVERAGE(C33:F33) -> 0.74338599
B34: Net Profit Margin | C34: =C29/C10 -> 0.518 | D34: =D29/D10 -> 0.51964017 | E34: =E29/E10 -> 0.52118672 | F34: =F29/F10 -> 0.52265389 | G34: =AVERAGE(C34:F34) -> 0.52037019
C38: =G29 -> 185381.06
C40: =G29/G10 -> 0.5205813

Sheet 🏦 Balance Sheet
B2: 🏦 BALANCE SHEET - FY 2025
B3: As at 31 December 2025 | All figures in USD ($)
B5: Item | C5: Current Year ($) | D5: Prior Year ($)
B6: ASSETS
B7: Current Assets
B8: Cash & Cash Equivalents | C8: ='💵 Cash Flow'!C28 -> 41695 | D8: 45000
B9: Accounts Receivable | C9: ='💰 Income Statement'!G10*'⚙️ Assumptions'!C30/365 -> 43903.228 | D9: 32000
B10: Inventory | C10: ='💰 Income Statement'!G15*'⚙️ Assumptions'!C32/365 -> 0 | D10: 28000
B11: Prepaid Expenses | C11: 8500 | D11: 7800
B12: Other Current Assets | C12: 3200 | D12: 2900
B13: TOTAL CURRENT ASSETS | C13: =SUM(C8:C12) -> 97298.228 | D13: =SUM(D8:D12) -> 115700
B14: Non-Current Assets
B15: Property, Plant & Equipment | C15: 180000 | D15: 175000
B16: Less: Accumulated Depreciation | C16: =-'⚙️ Assumptions'!C23*180000 -> -18000 | D16: -17500
B17: Intangible Assets | C17: 25000 | D17: 28000
B18: Long-term Investments | C18: 40000 | D18: 35000
B19: TOTAL NON-CURRENT ASSETS | C19: =SUM(C15:C18) -> 227000 | D19: =SUM(D15:D18) -> 238000
B20: ★ TOTAL ASSETS | C20: =C13+C19 -> 324298.23 | D20: =D13+D19 -> 353700
B22: LIABILITIES & EQUITY
B23: Current Liabilities
B24: Accounts Payable | C24: ='💰 Income Statement'!G15*'⚙️ Assumptions'!C31/365 -> 0 | D24: 18000
B25: Short-term Loans | C25: 20000 | D25: 20000
B26: Accrued Liabilities | C26: 9500 | D26: 8800
B27: Tax Payable | C27: ='💰 Income Statement'!G28 -> 79449.027 | D27: 5000
B28: TOTAL CURRENT LIABILITIES | C28: =SUM(C24:C27) -> 108949.03 | D28: =SUM(D24:D27) -> 51800
B29: Non-Current Liabilities
B30: Long-term Debt | C30: ='⚙️ Assumptions'!C33 -> 150000 | D30: 150000
B31: Deferred Tax Liabilities | C31: 4500 | D31: 3800
B32: TOTAL NON-CURRENT LIAB. | C32: =SUM(C30:C31) -> 154500 | D32: =SUM(D30:D31) -> 153800
B33: Shareholders' Equity
B34: Share Capital | C34: 100000 | D34: 100000
B35: Retained Earnings | C35: ='💰 Income Statement'!G29 -> 185381.06 | D35: 80000
B36: Other Reserves | C36: 12000 | D36: 10000
B37: TOTAL EQUITY | C37: =SUM(C34:C36) -> 297381.06 | D37: =SUM(D34:D36) -> 190000
B38: ★ TOTAL LIABILITIES & EQUITY | C38: =C28+C32+C37 -> 560830.09 | D38: =D28+D32+D37 -> 395600
B40: ✔ Balance Check (Assets = Liabilities + Equity) | C40: =IF(C20=C38,"✔ BALANCED","✖ CHECK ERRORS") -> ✖ CHECK ERRORS

Sheet 💵 Cash Flow
B2: 💵 CASH FLOW STATEMENT - FY 2025
B3: January – December 2025 | Direct Method
B5: Description | C5: Q1 ($) | D5: Q2 ($) | E5: Annual Total ($)
B6: OPERATING ACTIVITIES
B7: Net Profit | C7: ='💰 Income Statement'!C29 -> 38850 | D7: ='💰 Income Statement'!D29 -> 43467.9 | E7: =SUM(C7:D7) -> 82317.9
B8: Add: Depreciation | C8: ='💰 Income Statement'!C21 -> 7500 | D8: ='💰 Income Statement'!D21 -> 8365 | E8: =SUM(C8:D8) -> 15865
B9: (Inc)/Dec in Accounts Receivable | C9: -8000 | D9: -2000 | E9: =SUM(C9:D9) -> -10000
B10: (Inc)/Dec in Inventory | C10: -5000 | D10: -1500 | E10: =SUM(C10:D10) -> -6500
B11: Inc/(Dec) in Accounts Payable | C11: 4000 | D11: 1000 | E11: =SUM(C11:D11) -> 5000
B12: Other Working Capital Changes | C12: -1000 | D12: -500 | E12: =SUM(C12:D12) -> -1500
B13: NET CASH FROM OPERATIONS | C13: =SUM(C7:C12) -> 36350 | D13: =SUM(D7:D12) -> 48832.9 | E13: =SUM(E7:E12) -> 85182.9
B14: INVESTING ACTIVITIES
B15: Purchase of Property & Equipment | C15: -25000 | D15: -10000 | E15: =SUM(C15:D15) -> -35000
B16: Proceeds from Asset Disposals | C16: 2000 | D16: 0 | E16: =SUM(C16:D16) -> 2000
B17: Purchase of Investments | C17: -5000 | D17: 0 | E17: =SUM(C17:D17) -> -5000
B18: NET CASH FROM INVESTING | C18: =SUM(C15:C17) -> -28000 | D18: =SUM(D15:D17) -> -10000 | E18: =SUM(E15:E17) -> -38000
B19: FINANCING ACTIVITIES
B20: Proceeds from Borrowings | C20: 10000 | D20: 0 | E20: =SUM(C20:D20) -> 10000
B21: Repayment of Loans | C21: -15000 | D21: -5000 | E21: =SUM(C21:D21) -> -20000
B22: Dividends Paid | C22: =-'💰 Income Statement'!C29*'⚙️ Assumptions'!C25 -> -11655 | D22: =-'💰 Income Statement'!D29*'⚙️ Assumptions'!C25 -> -13040.37 | E22: =C22+D22 -> -24695.37
B23: NET CASH FROM FINANCING | C23: =SUM(C20:C22) -> -16655 | D23: =SUM(D20:D22) -> -18040.37 | E23: =SUM(E20:E22) -> -34695.37
B24: CASH MOVEMENT SUMMARY
B25: Net Increase/(Decrease) in Cash | C25: =C13+C18+C23 -> -8305 | D25: =D13+D18+D23 -> 20792.53 | E25: =E13+E18+E23 -> 12487.53
B26: Opening Cash Balance | C26: ='⚙️ Assumptions'!C29 -> 50000 | D26: ='⚙️ Assumptions'!C29+D25 -> 70792.53 | E26: =C26 -> 50000
B27: ★ CLOSING CASH BALANCE
C28: ='⚙️ Assumptions'!C29+C25 -> 41695 | D28: =C28+D25 -> 62487.53 | E28: ='⚙️ Assumptions'!C29+E25 -> 62487.53

Sheet 📈 Budget vs Actual
B2: 📈 BUDGET VS ACTUAL ANALYSIS - FY 2025
B3: Variance Analysis | Blue = inputs | Favourable variances in green, unfavourable in red
B5: Category | C5: Budget ($) | D5: Actual ($) | E5: Variance ($) | F5: Var %
B6: REVENUE
B7: Product Revenue | C7: 200000 | D7: ='💰 Income Statement'!G7 -> 334552.96 | E7: =D7-C7 -> 134552.96 | F7: =E7/C7 -> 0.6727648
B8: Services Revenue | C8: 80000 | D8: ='💰 Income Statement'!G8 -> 0 | E8: =D8-C8 -> -80000 | F8: =E8/C8 -> -1
B9: Other Revenue | C9: 18000 | D9: ='💰 Income Statement'!G9 -> 21551 | E9: =D9-C9 -> 3551 | F9: =E9/C9 -> 0.19727778
B10: TOTAL REVENUE | C10: 298000 | D10: ='💰 Income Statement'!G10 -> 356103.96 | E10: =D10-C10 -> 58103.96 | F10: =E10/C10 -> 0.19497973
B11: EXPENSES
B12: Cost of Goods Sold | C12: 125000 | D12: ='💰 Income Statement'!G15 -> 0 | E12: =D12-C12 -> -125000 | F12: =E12/C12 -> -1
B13: Salaries & Wages | C13: 62000 | D13: ='💰 Income Statement'!G18 -> 0 | E13: =D13-C13 -> -62000 | F13: =E13/C13 -> -1
B14: Marketing | C14: 20000 | D14: ='💰 Income Statement'!G19 -> 24927.277 | E14: =D14-C14 -> 4927.2772 | F14: =E14/C14 -> 0.24636386
B15: Admin & Overhead | C15: 14000 | D15: ='💰 Income Statement'!G20 -> 17805.198 | E15: =D15-C15 -> 3805.198 | F15: =E15/C15 -> 0.27179986
B16: TOTAL EXPENSES | C16: 221000 | D16: =SUM(D12:D15) -> 42732.475 | E16: =D16-C16 -> -178267.52 | F16: =E16/C16 -> -0.80664038
B17: PROFITABILITY
B18: Gross Profit | C18: 90000 | D18: ='💰 Income Statement'!G16 -> 356103.96 | E18: =D18-C18 -> 266103.96 | F18: =E18/C18 -> 2.9567107
B19: Net Profit | C19: 58000 | D19: ='💰 Income Statement'!G29 -> 185381.06 | E19: =D19-C19 -> 127381.06 | F19: =E19/C19 -> 2.1962252
B22: 📌 Color Guide: Blue = Input cells | Black = Formula cells | Green variance = favourable | Red variance = unfavourable
